dash_resumable_upload_bb
