Metadata-Version: 1.1
Name: dash-resumable-upload-bb
Version: 0.0.6
Summary: Dash Resumable Upload component for large files.
Home-page: UNKNOWN
Author: marrenr
Author-email: UNKNOWN
License: MIT
Download-URL: https://github.com/den-mi/dash-resumable-upload-bb/archive/0.0.6.tar.gz
Platform: UNKNOWN
